eisenmp/__init__.py
eisenmp/eisenmp_procenv.py
eisenmp/eisenmp_q_coll.py
eisenmp/eisenmp_worker_loader.py
eisenmp/utils/__init__.py
eisenmp/utils/eisenmp_constants.py
eisenmp/utils/eisenmp_info.py
eisenmp/utils/eisenmp_utils.py
eisenmp-1.0.dist-info/LICENSE
eisenmp-1.0.dist-info/LICENSE.rst
eisenmp-1.0.dist-info/METADATA
eisenmp-1.0.dist-info/WHEEL
eisenmp-1.0.dist-info/top_level.txt
eisenmp-1.0.dist-info/zip-safe
eisenmp-1.0.dist-info/RECORD
