Metadata-Version: 2.1
Name: eisenmp
Version: 1.0
Summary: Multiprocess Framework for Server and Mobiles; run your generator output and server on every CPU core,
Author: René Horn
Author-email: René Horn <rene_horn@gmx.net>
License: BSD 3-Clause License
Project-URL: homepage, https://github.com/44xtc44
Project-URL: documentation, https://eisenmp.readthedocs.io/
Project-URL: repository, https://github.com/44xtc44/eisenmp
Keywords: multiprocess framework,python multiprocessor framework
Classifier: Programming Language :: Python :: 3
Classifier: Operating System :: OS Independent
Classifier: Development Status :: 5 - Production/Stable
Requires-Python: >=3.7
License-File: LICENSE
License-File: LICENSE.rst
Provides-Extra: testing
Requires-Dist: pytest (>=6.0) ; extra == 'testing'
Requires-Dist: pytest-cov (>=2.0) ; extra == 'testing'
Requires-Dist: mypy (>=0.9.10) ; extra == 'testing'
Requires-Dist: flake8 (>=3.9) ; extra == 'testing'
Requires-Dist: tox (>=3.24) ; extra == 'testing'
